pypiron/__init__.py
pypiron/config.py
pypiron/gunicorn_conf.py
pypiron/index_gen.py
pypiron/main.py
pypiron/storage_backends.py
pypiron/utils.py
PypIron-0.0.1.dist-info/METADATA
PypIron-0.0.1.dist-info/WHEEL
PypIron-0.0.1.dist-info/top_level.txt
PypIron-0.0.1.dist-info/RECORD
