Metadata-Version: 2.1
Name: PypIron
Version: 0.0.1
Summary: A reliable, scalable pypi server
Home-page: https://github.com/brycedrennan/pypiron
Author: Bryce Drennan
Author-email: 
Keywords: pypi,packaging
Classifier: License :: OSI Approved :: MIT License
Requires-Python: >=3.7
Requires-Dist: boto3
Requires-Dist: fastapi
Requires-Dist: python-multipart
